Workbook
Name dates: #REF!
Name revenu: #REF!
Name signe: #REF!
Name tabl: '[1]Suivi clients'!$B$1:$C$13
Name tututut: '[1]Suivi clients'!$B$1:$C$13
Name zodiaque: VLOOKUP(DATE(1900,MONTH('[1]Suivi clients'!XFD1),DAY('[1]Suivi clients'!XFD1)),tabl,2,1)
Name Zozo: VLOOKUP(DATE(1900,MONTH('[1]Suivi clients'!XFD1),DAY('[1]Suivi clients'!XFD1)),tututut,2,1)

Sheet REVENUS
B1: ÉTAT CIVIL
B3: Nom | G3: Nom
B4: Prénom | G4: Prénom
B5: Email | G5: Email
B6: Téléphone | G6: Téléphone
B7: Date de naissance | G7: Date de naissance
B8: Situation familiale | D8: Régime
B9: Nombre d'enfants | D9: Ages
B10: Parts fiscales
B12: Remarques :
B14: REVENUS / FISCALITÉ
B16: Profession | G16: Profession
B17: Entreprise | G17: Entreprise
B18: Ancienneté | G18: Ancienneté
B19: Régime | G19: Régime
B20: Revenus | C20: Fixe annuel | E20: Variable | G20: Revenus | H20: Fixe annuel | J20: Variable
B21: Brut Annuel | D21: =D20+F20 -> 0 | G21: Brut Annuel | I21: =SUM(I20+K20) -> 0
B23: Remarques :
B25: IMPÔT SUR LE REVENU
B27: Réductions
B28: Investissements fiscaux
B30: Remarques :

Sheet IMMOBILIER
D2: PATRIMOINE IMMOBILIER
B3: RÉSIDENCE PRINCIPALE
B5: Adresse
B6: Situation | E6: Loyer/Mensualité
B7: Valeur estimée | E7: Valeur d'achat
B8: K emprunté | E8: Date d'achat
B9: Capital restant dû | E9: Durée d'emprunt
B10: Remarques :
B12: RÉSIDENCE SECONDAIRE/LOCATIVE
B14: Adresse :
B15: Valeur estimée | E15: Valeur d'achat
B16: K emprunté | E16: Mensualités
B17: Capital restant dû | E17: Durée d'emprunt
B18: Loyers perçus
B19: Remarques :
B21: AUTRES CRÉDITS
B23: Désignation
B24: K emprunté | D24: CRD | F24: Mensualités | H24: Durée
B26: Désignation
B27: K emprunté | D27: CRD | F27: Mensualités | H27: Durée

Sheet FINANCIER
D2: PATRIMOINE FINANCIER
B4: Détenteur | C4: Type de produit | D4: Valeur actuelle | E4: Date de souscription | F4: Remarques
C5: Livret A
C6: Compte courant
C7: PEE
C8: Assurance Vie
C9: PEA
C10: PEA-PME
C11: Compte titre
C12: Compte titre
C13: Compte titre actions inter
C14: AISA
C15: AISA
C16: Fonds de pension UK
B26: Valeur Totale | D26: =SUM(D5:D25) -> 0

Sheet Tx d'endettement
B2: Investisseur Calcul du Taux d'Endettement
B4: Revenus du/des salariés | E4: Montant potentiel en SCPI (sans prendre en compte l'endettement)
B5: Revenu mensuel NET | C5: =(REVENUS!D21*0.77)/12+(REVENUS!I21*0.77)/12 -> 0 | E5: =IF(IMMOBILIER!D6="Locataire",(C5*12*5)-C19,(C5*12*8)-C7-C19) -> 0
B6: loyer HC | C6: =IMMOBILIER!F6 -> 0
B7: CRD | C7: =IMMOBILIER!D9 -> 0
B8: Endettement après les revenus | C8: =C6/C5 -> #DIV/0!
B10: Autre(s) bien(s) immobilier(s) | E10: Taux d'endettement post-opération en SCPI
B11: Loyers perçus réels | C11: =IMMOBILIER!D18 -> 0 | E11: 75000 | F11: =($C$6+$C$13+$C$18+Formules!B24)/($C$5+$C$12+Formules!D24) -> 1.6666667
B12: Loyers perçus retenus | C12: =C11*0.7 -> 0 | E12: 100000 | F12: =($C$6+$C$13+$C$18+Formules!B25)/($C$5+$C$12+Formules!D25) -> 1.643739
B13: Crédit | C13: =IMMOBILIER!F16 -> 0 | E13: 150000 | F13: =($C$6+$C$13+$C$18+Formules!B26)/($C$5+$C$12+Formules!D26) -> 1.6313214
B14: CRD | C14: =IMMOBILIER!D17 -> 0 | E14: 200000 | F14: =($C$6+$C$13+$C$18+Formules!B27)/($C$5+$C$12+Formules!D27) -> 1.6182356
B15: Endettement après les autres actifs | C15: =(C6+C13)/(C12+C5) -> #DIV/0! | E15: 250000 | F15: =($C$6+$C$13+$C$18+Formules!B28)/($C$5+$C$12+Formules!D28) -> 1.6144244
E16: 300000 | F16: =($C$6+$C$13+$C$18+Formules!B29)/($C$5+$C$12+Formules!D29) -> 1.6155089
B17: Autre(s) crédit(s)
B18: Mensualité | C18: =IMMOBILIER!G24+IMMOBILIER!G27 -> 0
B19: CRD | C19: =IMMOBILIER!E24+IMMOBILIER!E27 -> 0
B20: Endettement total | C20: =(C6+C13+C18)/(C5+C12) -> #DIV/0!

Sheet OBJECTIFS ET EFFORT
B3: US person? | C3: Non | D3: Politiquement exposé ? | E3: Non | F3: Biens divers ? | G3: Non
B7: EFFORT D'EPARGNE
B10: OBJECTIFS

Sheet SIMULATEUR
C2: Remplir les cases jaunes uniquement
B4: Situation des emprunteurs | C4: Charges (loyers et/ou crédits) | D4: =IMMOBILIER!F6+IMMOBILIER!F16+IMMOBILIER!G24+IMMOBILIER!G27 -> 0 | E4: Revenus Mr | F4: Revenus Mme
C5: Revenus avant impots (variable inclus uniquement si + de 3 ans) | D5: =E5+F5 -> 0 | E5: ='Tx d''endettement'!C5 -> 0 | F5: =REVENUS!I21*0.77/12 -> 0
C6: Propriétaire ou locataire ? | D6: Propriétaire
C7: Célibataire ou en couple ? | D7: Célibataire
C8: Nombre d'enfants à charge | D8: =REVENUS!C9 -> 0
C9: Loyers mensuels percus sur investissements locatifs | D9: =IMMOBILIER!D18 -> 0
C10: Capital Restant dû (tous prêts confondus) | D10: =IMMOBILIER!D9+IMMOBILIER!D17+IMMOBILIER!E24+IMMOBILIER!E27 -> 0
C11: Montant d'épargne | D11: =FINANCIER!D26 -> 0
B13: Investissement SCPI | C13: Montant d'investissement SCPI | D13: 200000
C14: Taux hors assurance | D14: 0.0495
C15: Durée du prêt en mois | D15: 300
C16: Mensualité du prêt de la SCPI | D16: =PMT(D14/12,D15,-D13) -> 1163.3612
C17: Revenus de la SCPI pris en compte | D17: =(D13*0.055/12)*70% -> 641.66667
B19: Ratios emprunteur après opération à valider | C19: Taux d'endettement après opération SCPI | D19: =(D4+D16)/(D5+D17+(0.7*D9)) -> 1.8130305 | E19: doit etre < 45%
C20: Ratio passif | D20: =IF(D6=Formules!C7,8*D5*12-(D13+D10),5*D5*12-(D13+D10)) -> -200000 | E20: doit être > 0
C21: Restant à vivre | D21: =(D5+D17+(0.7*D9))-(D4+D16) -> -521.69456 | E21: doit être > 1500 si celib, 2000 pour un couple, 2500 couple avec enfant + 500 par enfant
C22: Ratio d'épargne | D22: =D11/D13 -> 0 | E22: doit etre > 10% (idealement >15%)
C24: ,
B25: Taux : 25 ans : 2.50% // 20 ans 2.30%
B26: Soucriptions de 75k€ mini et acces au SCPI externe à partir de 150 k€
B27: Frais de dossier : 600€
B28: Frais d’intermédiation : 1000€
B29: Frais de garantie : 350€
B30: SCI OU EN DIRECT ( pas de SCI pour les célibataires locataires ou hébergé à titre gratuit hormis profils patrimoniaux )
B31: Pas de domiciliation de salaire
B32: Locataire ou propriétaire Fr à Nantissement des parts
B33: Prof liberales acceptées uniquement avocats et medecins
B34: Montant mini d’épargne à titre indicatif entre 10 et 15 %
B35: Taux endettement Max : 45% après opération

Sheet Formules
A6: calcul du restant a vivre | B6: Nombre d'enfants | C6: Propriétaires RP | D6: Investissement en couple ou seul | E6: Taux d'endettement après opération SCPI | F6: Ratio passif | G6: Restant à vivre | H6: Ratio d'épargne | I6: Situation familiale | J6: Régime | K6: Parts fiscales
A7: =IF(SIMULATEUR!D7=Formules!D7,2000+(SIMULATEUR!D8*500),1500+(SIMULATEUR!D8*500)) -> 1500 | B7: 0 | D7: En couple | E7: 0.45 | F7: 0 | G7: 1500 | H7: 0.15 | K7: 1
B8: 1 | C8: Propriétaire | D8: Célibataire | I8: Célibataire | J8: Communauté | K8: 1.5
B9: 2 | C9: Locataire | I9: Pacsé | J9: Société aux Acquets | K9: 2
B10: 3 | C10: Logé à titre gratuit | I10: Marié | J10: Séparation | K10: 2.5
B11: 4 | I11: Concubinage | K11: 3
B12: 5 | K12: 3.5
B13: 6
B14: 7
B15: 8
B16: 9
B17: 10
A23: Montant en SCPI | B23: Charges de crédit mensuelles SCPI | C23: Loyers à 5% | D23: loyers retenus
A24: 75K | B24: 350 | C24: 300 | D24: =C24*70% -> 210
A25: 100K | B25: 466 | C25: 405 | D25: =C25*70% -> 283.5
A26: 150K | B26: 700 | C26: 613 | D26: =C26*70% -> 429.1
A27: 200K | B27: 930 | C27: 821 | D27: =C27*70% -> 574.7
A28: 250K | B28: 1164 | C28: 1030 | D28: =C28*70% -> 721
A29: 300K | B29: 1400 | C29: 1238 | D29: =C29*70% -> 866.6
